shikithon/__init__.py
shikithon/api.py
shikithon/base_client.py
shikithon/decorators/__init__.py
shikithon/decorators/exceptions_handler.py
shikithon/decorators/method_endpoint.py
shikithon/endpoints.py
shikithon/enums/__init__.py
shikithon/enums/anime.py
shikithon/enums/club.py
shikithon/enums/comment.py
shikithon/enums/enhanced_enum.py
shikithon/enums/favorite.py
shikithon/enums/history.py
shikithon/enums/manga.py
shikithon/enums/message.py
shikithon/enums/person.py
shikithon/enums/ranobe.py
shikithon/enums/request.py
shikithon/enums/response.py
shikithon/enums/review.py
shikithon/enums/style.py
shikithon/enums/topic.py
shikithon/enums/user_rate.py
shikithon/enums/video.py
shikithon/exceptions/__init__.py
shikithon/exceptions/already_running_client.py
shikithon/exceptions/invalid_content_type.py
shikithon/exceptions/missing_app_variable.py
shikithon/exceptions/retry_later.py
shikithon/exceptions/shikimori_api_response_error.py
shikithon/exceptions/shikithon_exception.py
shikithon/exceptions/store_exception.py
shikithon/models/__init__.py
shikithon/models/abuse_response.py
shikithon/models/achievement.py
shikithon/models/activity.py
shikithon/models/anime.py
shikithon/models/ban.py
shikithon/models/calendar_event.py
shikithon/models/character.py
shikithon/models/club.py
shikithon/models/club_image.py
shikithon/models/comment.py
shikithon/models/constants.py
shikithon/models/created_user_image.py
shikithon/models/critique.py
shikithon/models/date.py
shikithon/models/dialog.py
shikithon/models/favourite.py
shikithon/models/favourites.py
shikithon/models/forum.py
shikithon/models/franchise_tree.py
shikithon/models/genre.py
shikithon/models/history.py
shikithon/models/image.py
shikithon/models/link.py
shikithon/models/linked_topic.py
shikithon/models/logo.py
shikithon/models/manga.py
shikithon/models/message.py
shikithon/models/person.py
shikithon/models/publisher.py
shikithon/models/ranobe.py
shikithon/models/rating.py
shikithon/models/rating_list.py
shikithon-2.6.2.dist-info/LICENSE
shikithon-2.6.2.dist-info/METADATA
shikithon-2.6.2.dist-info/WHEEL
shikithon-2.6.2.dist-info/RECORD
