Metadata-Version: 2.1
Name: shikithon
Version: 2.6.2
Summary: Yet another Python wrapper for Shikimori API
Home-page: https://github.com/SecondThundeR/shikithon
License: MIT
Keywords: Python,Shikimori,API
Author: SecondThundeR
Author-email: awayfromgalaxy@gmail.com
Requires-Python: >=3.8.10,<4.0.0
Classifier: License :: OSI Approved :: MIT License
Classifier: Operating System :: OS Independent
Classifier: Programming Language :: Python :: 3
Classifier: Programming Language :: Python :: 3.9
Classifier: Programming Language :: Python :: 3.10
Classifier: Programming Language :: Python :: 3.11
Classifier: Programming Language :: Python :: 3.12
Requires-Dist: aiohttp (>=3.9.1,<4.0.0)
Requires-Dist: backoff (>=2.2.1,<3.0.0)
Requires-Dist: loguru (>=0.7.2,<0.8.0)
Requires-Dist: pydantic (>=2.5.3,<3.0.0)
Requires-Dist: typing-extensions (>=4.9.0,<5.0.0)
Requires-Dist: validators (>=0.22.0,<0.23.0)
Project-URL: Documentation, https://github.com/SecondThundeR/shikithon/README.md
Project-URL: Repository, https://github.com/SecondThundeR/shikithon
